{
  "weeds": {
    "98118": {
      "ZIP": 98118,
      "module": "weeds",
      "tier": "Premium",
      "monthly_price_usd": 99,
      "annual_unique_total_2025": 241,
      "expected_leads_per_month": 20.08,
      "bonus_low_activity": false,
      "tier_basis": "2025 unique TOTAL properties (deduped by address+ZIP)",
      "note": null
    },
    "98115": {
      "ZIP": 98115,
      "module": "weeds",
      "tier": "Premium",
      "monthly_price_usd": 99,
      "annual_unique_total_2025": 214,
      "expected_leads_per_month": 17.83,
      "bonus_low_activity": false,
      "tier_basis": "2025 unique TOTAL properties (deduped by address+ZIP)",
      "note": null
    },
    "98103": {
      "ZIP": 98103,
      "module": "weeds",
      "tier": "Premium",
      "monthly_price_usd": 99,
      "annual_unique_total_2025": 203,
      "expected_leads_per_month": 16.92,
      "bonus_low_activity": false,
      "tier_basis": "2025 unique TOTAL properties (deduped by address+ZIP)",
      "note": null
    },
    "98144": {
      "ZIP": 98144,
      "module": "weeds",
      "tier": "Premium",
      "monthly_price_usd": 99,
      "annual_unique_total_2025": 148,
      "expected_leads_per_month": 12.33,
      "bonus_low_activity": false,
      "tier_basis": "2025 unique TOTAL properties (deduped by address+ZIP)",
      "note": null
    },
    "98117": {
      "ZIP": 98117,
      "module": "weeds",
      "tier": "Premium",
      "monthly_price_usd": 99,
      "annual_unique_total_2025": 138,
      "expected_leads_per_month": 11.5,
      "bonus_low_activity": false,
      "tier_basis": "2025 unique TOTAL properties (deduped by address+ZIP)",
      "note": null
    },
    "98107": {
      "ZIP": 98107,
      "module": "weeds",
      "tier": "High",
      "monthly_price_usd": 69,
      "annual_unique_total_2025": 129,
      "expected_leads_per_month": 10.75,
      "bonus_low_activity": false,
      "tier_basis": "2025 unique TOTAL properties (deduped by address+ZIP)",
      "note": null
    },
    "98105": {
      "ZIP": 98105,
      "module": "weeds",
      "tier": "High",
      "monthly_price_usd": 69,
      "annual_unique_total_2025": 126,
      "expected_leads_per_month": 10.5,
      "bonus_low_activity": false,
      "tier_basis": "2025 unique TOTAL properties (deduped by address+ZIP)",
      "note": null
    },
    "98116": {
      "ZIP": 98116,
      "module": "weeds",
      "tier": "High",
      "monthly_price_usd": 69,
      "annual_unique_total_2025": 126,
      "expected_leads_per_month": 10.5,
      "bonus_low_activity": false,
      "tier_basis": "2025 unique TOTAL properties (deduped by address+ZIP)",
      "note": null
    },
    "98122": {
      "ZIP": 98122,
      "module": "weeds",
      "tier": "High",
      "monthly_price_usd": 69,
      "annual_unique_total_2025": 124,
      "expected_leads_per_month": 10.33,
      "bonus_low_activity": false,
      "tier_basis": "2025 unique TOTAL properties (deduped by address+ZIP)",
      "note": null
    },
    "98199": {
      "ZIP": 98199,
      "module": "weeds",
      "tier": "High",
      "monthly_price_usd": 69,
      "annual_unique_total_2025": 120,
      "expected_leads_per_month": 10.0,
      "bonus_low_activity": false,
      "tier_basis": "2025 unique TOTAL properties (deduped by address+ZIP)",
      "note": null
    },
    "98106": {
      "ZIP": 98106,
      "module": "weeds",
      "tier": "High",
      "monthly_price_usd": 69,
      "annual_unique_total_2025": 119,
      "expected_leads_per_month": 9.92,
      "bonus_low_activity": false,
      "tier_basis": "2025 unique TOTAL properties (deduped by address+ZIP)",
      "note": null
    },
    "98126": {
      "ZIP": 98126,
      "module": "weeds",
      "tier": "High",
      "monthly_price_usd": 69,
      "annual_unique_total_2025": 115,
      "expected_leads_per_month": 9.58,
      "bonus_low_activity": false,
      "tier_basis": "2025 unique TOTAL properties (deduped by address+ZIP)",
      "note": null
    },
    "98108": {
      "ZIP": 98108,
      "module": "weeds",
      "tier": "High",
      "monthly_price_usd": 69,
      "annual_unique_total_2025": 111,
      "expected_leads_per_month": 9.25,
      "bonus_low_activity": false,
      "tier_basis": "2025 unique TOTAL properties (deduped by address+ZIP)",
      "note": null
    },
    "98119": {
      "ZIP": 98119,
      "module": "weeds",
      "tier": "High",
      "monthly_price_usd": 69,
      "annual_unique_total_2025": 107,
      "expected_leads_per_month": 8.92,
      "bonus_low_activity": false,
      "tier_basis": "2025 unique TOTAL properties (deduped by address+ZIP)",
      "note": null
    },
    "98112": {
      "ZIP": 98112,
      "module": "weeds",
      "tier": "High",
      "monthly_price_usd": 69,
      "annual_unique_total_2025": 104,
      "expected_leads_per_month": 8.67,
      "bonus_low_activity": false,
      "tier_basis": "2025 unique TOTAL properties (deduped by address+ZIP)",
      "note": null
    },
    "98102": {
      "ZIP": 98102,
      "module": "weeds",
      "tier": "High",
      "monthly_price_usd": 69,
      "annual_unique_total_2025": 89,
      "expected_leads_per_month": 7.42,
      "bonus_low_activity": false,
      "tier_basis": "2025 unique TOTAL properties (deduped by address+ZIP)",
      "note": null
    },
    "98109": {
      "ZIP": 98109,
      "module": "weeds",
      "tier": "High",
      "monthly_price_usd": 69,
      "annual_unique_total_2025": 85,
      "expected_leads_per_month": 7.08,
      "bonus_low_activity": false,
      "tier_basis": "2025 unique TOTAL properties (deduped by address+ZIP)",
      "note": null
    },
    "98136": {
      "ZIP": 98136,
      "module": "weeds",
      "tier": "High",
      "monthly_price_usd": 69,
      "annual_unique_total_2025": 82,
      "expected_leads_per_month": 6.83,
      "bonus_low_activity": false,
      "tier_basis": "2025 unique TOTAL properties (deduped by address+ZIP)",
      "note": null
    },
    "98125": {
      "ZIP": 98125,
      "module": "weeds",
      "tier": "Low",
      "monthly_price_usd": 39,
      "annual_unique_total_2025": 74,
      "expected_leads_per_month": 6.17,
      "bonus_low_activity": false,
      "tier_basis": "2025 unique TOTAL properties (deduped by address+ZIP)",
      "note": null
    },
    "98133": {
      "ZIP": 98133,
      "module": "weeds",
      "tier": "Low",
      "monthly_price_usd": 39,
      "annual_unique_total_2025": 54,
      "expected_leads_per_month": 4.5,
      "bonus_low_activity": false,
      "tier_basis": "2025 unique TOTAL properties (deduped by address+ZIP)",
      "note": null
    },
    "98178": {
      "ZIP": 98178,
      "module": "weeds",
      "tier": "Low",
      "monthly_price_usd": 39,
      "annual_unique_total_2025": 35,
      "expected_leads_per_month": 2.92,
      "bonus_low_activity": false,
      "tier_basis": "2025 unique TOTAL properties (deduped by address+ZIP)",
      "note": null
    },
    "98177": {
      "ZIP": 98177,
      "module": "weeds",
      "tier": "Low",
      "monthly_price_usd": 39,
      "annual_unique_total_2025": 21,
      "expected_leads_per_month": 1.75,
      "bonus_low_activity": false,
      "tier_basis": "2025 unique TOTAL properties (deduped by address+ZIP)",
      "note": null
    },
    "98146": {
      "ZIP": 98146,
      "module": "weeds",
      "tier": "Low",
      "monthly_price_usd": 39,
      "annual_unique_total_2025": 20,
      "expected_leads_per_month": 1.67,
      "bonus_low_activity": false,
      "tier_basis": "2025 unique TOTAL properties (deduped by address+ZIP)",
      "note": null
    },
    "98104": {
      "ZIP": 98104,
      "module": "weeds",
      "tier": "Bonus (low activity)",
      "monthly_price_usd": 10,
      "annual_unique_total_2025": 11,
      "expected_leads_per_month": 0.92,
      "bonus_low_activity": true,
      "tier_basis": "2025 unique TOTAL properties (deduped by address+ZIP)",
      "note": "Bonus ZIPs are <1 lead/mo historically; consider offering as add-on or free bonus."
    },
    "98121": {
      "ZIP": 98121,
      "module": "weeds",
      "tier": "Bonus (low activity)",
      "monthly_price_usd": 10,
      "annual_unique_total_2025": 9,
      "expected_leads_per_month": 0.75,
      "bonus_low_activity": true,
      "tier_basis": "2025 unique TOTAL properties (deduped by address+ZIP)",
      "note": "Bonus ZIPs are <1 lead/mo historically; consider offering as add-on or free bonus."
    },
    "98101": {
      "ZIP": 98101,
      "module": "weeds",
      "tier": "Bonus (low activity)",
      "monthly_price_usd": 10,
      "annual_unique_total_2025": 6,
      "expected_leads_per_month": 0.5,
      "bonus_low_activity": true,
      "tier_basis": "2025 unique TOTAL properties (deduped by address+ZIP)",
      "note": "Bonus ZIPs are <1 lead/mo historically; consider offering as add-on or free bonus."
    },
    "98134": {
      "ZIP": 98134,
      "module": "weeds",
      "tier": "Bonus (low activity)",
      "monthly_price_usd": 10,
      "annual_unique_total_2025": 5,
      "expected_leads_per_month": 0.42,
      "bonus_low_activity": true,
      "tier_basis": "2025 unique TOTAL properties (deduped by address+ZIP)",
      "note": "Bonus ZIPs are <1 lead/mo historically; consider offering as add-on or free bonus."
    },
    "98155": {
      "ZIP": 98155,
      "module": "weeds",
      "tier": null,
      "monthly_price_usd": 0,
      "annual_unique_total_2025": 0,
      "expected_leads_per_month": 0.0,
      "bonus_low_activity": false,
      "tier_basis": "2025 unique TOTAL properties (deduped by address+ZIP)",
      "note": null
    }
  },
  "dumping": {
    "98118": {
      "ZIP": 98118,
      "module": "dumping",
      "tier": "Premium",
      "monthly_price_usd": 129,
      "annual_unique_total_2025": 105,
      "expected_leads_per_month": 8.75,
      "bonus_low_activity": false,
      "tier_basis": "2025 unique TOTAL properties (deduped by address+ZIP)",
      "note": null
    },
    "98122": {
      "ZIP": 98122,
      "module": "dumping",
      "tier": "Premium",
      "monthly_price_usd": 129,
      "annual_unique_total_2025": 99,
      "expected_leads_per_month": 8.25,
      "bonus_low_activity": false,
      "tier_basis": "2025 unique TOTAL properties (deduped by address+ZIP)",
      "note": null
    },
    "98103": {
      "ZIP": 98103,
      "module": "dumping",
      "tier": "Premium",
      "monthly_price_usd": 129,
      "annual_unique_total_2025": 79,
      "expected_leads_per_month": 6.58,
      "bonus_low_activity": false,
      "tier_basis": "2025 unique TOTAL properties (deduped by address+ZIP)",
      "note": null
    },
    "98144": {
      "ZIP": 98144,
      "module": "dumping",
      "tier": "Premium",
      "monthly_price_usd": 129,
      "annual_unique_total_2025": 78,
      "expected_leads_per_month": 6.5,
      "bonus_low_activity": false,
      "tier_basis": "2025 unique TOTAL properties (deduped by address+ZIP)",
      "note": null
    },
    "98105": {
      "ZIP": 98105,
      "module": "dumping",
      "tier": "Premium",
      "monthly_price_usd": 129,
      "annual_unique_total_2025": 75,
      "expected_leads_per_month": 6.25,
      "bonus_low_activity": false,
      "tier_basis": "2025 unique TOTAL properties (deduped by address+ZIP)",
      "note": null
    },
    "98115": {
      "ZIP": 98115,
      "module": "dumping",
      "tier": "Premium",
      "monthly_price_usd": 129,
      "annual_unique_total_2025": 69,
      "expected_leads_per_month": 5.75,
      "bonus_low_activity": false,
      "tier_basis": "2025 unique TOTAL properties (deduped by address+ZIP)",
      "note": null
    },
    "98107": {
      "ZIP": 98107,
      "module": "dumping",
      "tier": "Premium",
      "monthly_price_usd": 129,
      "annual_unique_total_2025": 68,
      "expected_leads_per_month": 5.67,
      "bonus_low_activity": false,
      "tier_basis": "2025 unique TOTAL properties (deduped by address+ZIP)",
      "note": null
    },
    "98106": {
      "ZIP": 98106,
      "module": "dumping",
      "tier": "Premium",
      "monthly_price_usd": 129,
      "annual_unique_total_2025": 67,
      "expected_leads_per_month": 5.58,
      "bonus_low_activity": false,
      "tier_basis": "2025 unique TOTAL properties (deduped by address+ZIP)",
      "note": null
    },
    "98125": {
      "ZIP": 98125,
      "module": "dumping",
      "tier": "High",
      "monthly_price_usd": 89,
      "annual_unique_total_2025": 63,
      "expected_leads_per_month": 5.25,
      "bonus_low_activity": false,
      "tier_basis": "2025 unique TOTAL properties (deduped by address+ZIP)",
      "note": null
    },
    "98109": {
      "ZIP": 98109,
      "module": "dumping",
      "tier": "High",
      "monthly_price_usd": 89,
      "annual_unique_total_2025": 59,
      "expected_leads_per_month": 4.92,
      "bonus_low_activity": false,
      "tier_basis": "2025 unique TOTAL properties (deduped by address+ZIP)",
      "note": null
    },
    "98108": {
      "ZIP": 98108,
      "module": "dumping",
      "tier": "High",
      "monthly_price_usd": 89,
      "annual_unique_total_2025": 56,
      "expected_leads_per_month": 4.67,
      "bonus_low_activity": false,
      "tier_basis": "2025 unique TOTAL properties (deduped by address+ZIP)",
      "note": null
    },
    "98117": {
      "ZIP": 98117,
      "module": "dumping",
      "tier": "High",
      "monthly_price_usd": 89,
      "annual_unique_total_2025": 56,
      "expected_leads_per_month": 4.67,
      "bonus_low_activity": false,
      "tier_basis": "2025 unique TOTAL properties (deduped by address+ZIP)",
      "note": null
    },
    "98102": {
      "ZIP": 98102,
      "module": "dumping",
      "tier": "High",
      "monthly_price_usd": 89,
      "annual_unique_total_2025": 52,
      "expected_leads_per_month": 4.33,
      "bonus_low_activity": false,
      "tier_basis": "2025 unique TOTAL properties (deduped by address+ZIP)",
      "note": null
    },
    "98133": {
      "ZIP": 98133,
      "module": "dumping",
      "tier": "High",
      "monthly_price_usd": 89,
      "annual_unique_total_2025": 47,
      "expected_leads_per_month": 3.92,
      "bonus_low_activity": false,
      "tier_basis": "2025 unique TOTAL properties (deduped by address+ZIP)",
      "note": null
    },
    "98116": {
      "ZIP": 98116,
      "module": "dumping",
      "tier": "High",
      "monthly_price_usd": 89,
      "annual_unique_total_2025": 45,
      "expected_leads_per_month": 3.75,
      "bonus_low_activity": false,
      "tier_basis": "2025 unique TOTAL properties (deduped by address+ZIP)",
      "note": null
    },
    "98104": {
      "ZIP": 98104,
      "module": "dumping",
      "tier": "High",
      "monthly_price_usd": 89,
      "annual_unique_total_2025": 41,
      "expected_leads_per_month": 3.42,
      "bonus_low_activity": false,
      "tier_basis": "2025 unique TOTAL properties (deduped by address+ZIP)",
      "note": null
    },
    "98121": {
      "ZIP": 98121,
      "module": "dumping",
      "tier": "Low",
      "monthly_price_usd": 49,
      "annual_unique_total_2025": 34,
      "expected_leads_per_month": 2.83,
      "bonus_low_activity": false,
      "tier_basis": "2025 unique TOTAL properties (deduped by address+ZIP)",
      "note": null
    },
    "98119": {
      "ZIP": 98119,
      "module": "dumping",
      "tier": "Low",
      "monthly_price_usd": 49,
      "annual_unique_total_2025": 32,
      "expected_leads_per_month": 2.67,
      "bonus_low_activity": false,
      "tier_basis": "2025 unique TOTAL properties (deduped by address+ZIP)",
      "note": null
    },
    "98126": {
      "ZIP": 98126,
      "module": "dumping",
      "tier": "Low",
      "monthly_price_usd": 49,
      "annual_unique_total_2025": 32,
      "expected_leads_per_month": 2.67,
      "bonus_low_activity": false,
      "tier_basis": "2025 unique TOTAL properties (deduped by address+ZIP)",
      "note": null
    },
    "98136": {
      "ZIP": 98136,
      "module": "dumping",
      "tier": "Low",
      "monthly_price_usd": 49,
      "annual_unique_total_2025": 20,
      "expected_leads_per_month": 1.67,
      "bonus_low_activity": false,
      "tier_basis": "2025 unique TOTAL properties (deduped by address+ZIP)",
      "note": null
    },
    "98199": {
      "ZIP": 98199,
      "module": "dumping",
      "tier": "Low",
      "monthly_price_usd": 49,
      "annual_unique_total_2025": 20,
      "expected_leads_per_month": 1.67,
      "bonus_low_activity": false,
      "tier_basis": "2025 unique TOTAL properties (deduped by address+ZIP)",
      "note": null
    },
    "98112": {
      "ZIP": 98112,
      "module": "dumping",
      "tier": "Low",
      "monthly_price_usd": 49,
      "annual_unique_total_2025": 19,
      "expected_leads_per_month": 1.58,
      "bonus_low_activity": false,
      "tier_basis": "2025 unique TOTAL properties (deduped by address+ZIP)",
      "note": null
    },
    "98178": {
      "ZIP": 98178,
      "module": "dumping",
      "tier": "Low",
      "monthly_price_usd": 49,
      "annual_unique_total_2025": 19,
      "expected_leads_per_month": 1.58,
      "bonus_low_activity": false,
      "tier_basis": "2025 unique TOTAL properties (deduped by address+ZIP)",
      "note": null
    },
    "98101": {
      "ZIP": 98101,
      "module": "dumping",
      "tier": "Low",
      "monthly_price_usd": 49,
      "annual_unique_total_2025": 17,
      "expected_leads_per_month": 1.42,
      "bonus_low_activity": false,
      "tier_basis": "2025 unique TOTAL properties (deduped by address+ZIP)",
      "note": null
    },
    "98134": {
      "ZIP": 98134,
      "module": "dumping",
      "tier": "Bonus (low activity)",
      "monthly_price_usd": 10,
      "annual_unique_total_2025": 9,
      "expected_leads_per_month": 0.75,
      "bonus_low_activity": true,
      "tier_basis": "2025 unique TOTAL properties (deduped by address+ZIP)",
      "note": "Bonus ZIPs are <1 lead/mo historically; consider offering as add-on or free bonus."
    },
    "98177": {
      "ZIP": 98177,
      "module": "dumping",
      "tier": "Bonus (low activity)",
      "monthly_price_usd": 10,
      "annual_unique_total_2025": 9,
      "expected_leads_per_month": 0.75,
      "bonus_low_activity": true,
      "tier_basis": "2025 unique TOTAL properties (deduped by address+ZIP)",
      "note": "Bonus ZIPs are <1 lead/mo historically; consider offering as add-on or free bonus."
    },
    "98146": {
      "ZIP": 98146,
      "module": "dumping",
      "tier": "Bonus (low activity)",
      "monthly_price_usd": 10,
      "annual_unique_total_2025": 8,
      "expected_leads_per_month": 0.67,
      "bonus_low_activity": true,
      "tier_basis": "2025 unique TOTAL properties (deduped by address+ZIP)",
      "note": "Bonus ZIPs are <1 lead/mo historically; consider offering as add-on or free bonus."
    },
    "98191": {
      "ZIP": 98191,
      "module": "dumping",
      "tier": "Bonus (low activity)",
      "monthly_price_usd": 10,
      "annual_unique_total_2025": 2,
      "expected_leads_per_month": 0.17,
      "bonus_low_activity": true,
      "tier_basis": "2025 unique TOTAL properties (deduped by address+ZIP)",
      "note": "Bonus ZIPs are <1 lead/mo historically; consider offering as add-on or free bonus."
    },
    "98113": {
      "ZIP": 98113,
      "module": "dumping",
      "tier": null,
      "monthly_price_usd": 0,
      "annual_unique_total_2025": 0,
      "expected_leads_per_month": 0.0,
      "bonus_low_activity": false,
      "tier_basis": "2025 unique TOTAL properties (deduped by address+ZIP)",
      "note": null
    },
    "98155": {
      "ZIP": 98155,
      "module": "dumping",
      "tier": null,
      "monthly_price_usd": 0,
      "annual_unique_total_2025": 0,
      "expected_leads_per_month": 0.0,
      "bonus_low_activity": false,
      "tier_basis": "2025 unique TOTAL properties (deduped by address+ZIP)",
      "note": null
    },
    "98174": {
      "ZIP": 98174,
      "module": "dumping",
      "tier": null,
      "monthly_price_usd": 0,
      "annual_unique_total_2025": 0,
      "expected_leads_per_month": 0.0,
      "bonus_low_activity": false,
      "tier_basis": "2025 unique TOTAL properties (deduped by address+ZIP)",
      "note": null
    },
    "98181": {
      "ZIP": 98181,
      "module": "dumping",
      "tier": null,
      "monthly_price_usd": 0,
      "annual_unique_total_2025": 0,
      "expected_leads_per_month": 0.0,
      "bonus_low_activity": false,
      "tier_basis": "2025 unique TOTAL properties (deduped by address+ZIP)",
      "note": null
    }
  },
  "vacant": {
    "98118": {
      "ZIP": 98118,
      "module": "vacant",
      "tier": "Premium",
      "monthly_price_usd": 149,
      "annual_unique_total_2025": 70,
      "expected_leads_per_month": 5.83,
      "bonus_low_activity": false,
      "tier_basis": "2025 unique TOTAL properties (deduped by address+ZIP)",
      "note": null
    },
    "98144": {
      "ZIP": 98144,
      "module": "vacant",
      "tier": "Premium",
      "monthly_price_usd": 149,
      "annual_unique_total_2025": 48,
      "expected_leads_per_month": 4.0,
      "bonus_low_activity": false,
      "tier_basis": "2025 unique TOTAL properties (deduped by address+ZIP)",
      "note": null
    },
    "98103": {
      "ZIP": 98103,
      "module": "vacant",
      "tier": "Premium",
      "monthly_price_usd": 149,
      "annual_unique_total_2025": 44,
      "expected_leads_per_month": 3.67,
      "bonus_low_activity": false,
      "tier_basis": "2025 unique TOTAL properties (deduped by address+ZIP)",
      "note": null
    },
    "98106": {
      "ZIP": 98106,
      "module": "vacant",
      "tier": "Premium",
      "monthly_price_usd": 149,
      "annual_unique_total_2025": 42,
      "expected_leads_per_month": 3.5,
      "bonus_low_activity": false,
      "tier_basis": "2025 unique TOTAL properties (deduped by address+ZIP)",
      "note": null
    },
    "98122": {
      "ZIP": 98122,
      "module": "vacant",
      "tier": "Premium",
      "monthly_price_usd": 149,
      "annual_unique_total_2025": 38,
      "expected_leads_per_month": 3.17,
      "bonus_low_activity": false,
      "tier_basis": "2025 unique TOTAL properties (deduped by address+ZIP)",
      "note": null
    },
    "98125": {
      "ZIP": 98125,
      "module": "vacant",
      "tier": "Premium",
      "monthly_price_usd": 149,
      "annual_unique_total_2025": 36,
      "expected_leads_per_month": 3.0,
      "bonus_low_activity": false,
      "tier_basis": "2025 unique TOTAL properties (deduped by address+ZIP)",
      "note": null
    },
    "98107": {
      "ZIP": 98107,
      "module": "vacant",
      "tier": "High",
      "monthly_price_usd": 109,
      "annual_unique_total_2025": 34,
      "expected_leads_per_month": 2.83,
      "bonus_low_activity": false,
      "tier_basis": "2025 unique TOTAL properties (deduped by address+ZIP)",
      "note": null
    },
    "98108": {
      "ZIP": 98108,
      "module": "vacant",
      "tier": "High",
      "monthly_price_usd": 109,
      "annual_unique_total_2025": 32,
      "expected_leads_per_month": 2.67,
      "bonus_low_activity": false,
      "tier_basis": "2025 unique TOTAL properties (deduped by address+ZIP)",
      "note": null
    },
    "98115": {
      "ZIP": 98115,
      "module": "vacant",
      "tier": "High",
      "monthly_price_usd": 109,
      "annual_unique_total_2025": 29,
      "expected_leads_per_month": 2.42,
      "bonus_low_activity": false,
      "tier_basis": "2025 unique TOTAL properties (deduped by address+ZIP)",
      "note": null
    },
    "98105": {
      "ZIP": 98105,
      "module": "vacant",
      "tier": "High",
      "monthly_price_usd": 109,
      "annual_unique_total_2025": 27,
      "expected_leads_per_month": 2.25,
      "bonus_low_activity": false,
      "tier_basis": "2025 unique TOTAL properties (deduped by address+ZIP)",
      "note": null
    },
    "98117": {
      "ZIP": 98117,
      "module": "vacant",
      "tier": "High",
      "monthly_price_usd": 109,
      "annual_unique_total_2025": 27,
      "expected_leads_per_month": 2.25,
      "bonus_low_activity": false,
      "tier_basis": "2025 unique TOTAL properties (deduped by address+ZIP)",
      "note": null
    },
    "98116": {
      "ZIP": 98116,
      "module": "vacant",
      "tier": "High",
      "monthly_price_usd": 109,
      "annual_unique_total_2025": 23,
      "expected_leads_per_month": 1.92,
      "bonus_low_activity": false,
      "tier_basis": "2025 unique TOTAL properties (deduped by address+ZIP)",
      "note": null
    },
    "98126": {
      "ZIP": 98126,
      "module": "vacant",
      "tier": "High",
      "monthly_price_usd": 109,
      "annual_unique_total_2025": 23,
      "expected_leads_per_month": 1.92,
      "bonus_low_activity": false,
      "tier_basis": "2025 unique TOTAL properties (deduped by address+ZIP)",
      "note": null
    },
    "98133": {
      "ZIP": 98133,
      "module": "vacant",
      "tier": "High",
      "monthly_price_usd": 109,
      "annual_unique_total_2025": 23,
      "expected_leads_per_month": 1.92,
      "bonus_low_activity": false,
      "tier_basis": "2025 unique TOTAL properties (deduped by address+ZIP)",
      "note": null
    },
    "98109": {
      "ZIP": 98109,
      "module": "vacant",
      "tier": "Low",
      "monthly_price_usd": 69,
      "annual_unique_total_2025": 20,
      "expected_leads_per_month": 1.67,
      "bonus_low_activity": false,
      "tier_basis": "2025 unique TOTAL properties (deduped by address+ZIP)",
      "note": null
    },
    "98102": {
      "ZIP": 98102,
      "module": "vacant",
      "tier": "Low",
      "monthly_price_usd": 69,
      "annual_unique_total_2025": 17,
      "expected_leads_per_month": 1.42,
      "bonus_low_activity": false,
      "tier_basis": "2025 unique TOTAL properties (deduped by address+ZIP)",
      "note": null
    },
    "98119": {
      "ZIP": 98119,
      "module": "vacant",
      "tier": "Low",
      "monthly_price_usd": 69,
      "annual_unique_total_2025": 14,
      "expected_leads_per_month": 1.17,
      "bonus_low_activity": false,
      "tier_basis": "2025 unique TOTAL properties (deduped by address+ZIP)",
      "note": null
    },
    "98104": {
      "ZIP": 98104,
      "module": "vacant",
      "tier": "Low",
      "monthly_price_usd": 69,
      "annual_unique_total_2025": 13,
      "expected_leads_per_month": 1.08,
      "bonus_low_activity": false,
      "tier_basis": "2025 unique TOTAL properties (deduped by address+ZIP)",
      "note": null
    },
    "98121": {
      "ZIP": 98121,
      "module": "vacant",
      "tier": "Low",
      "monthly_price_usd": 69,
      "annual_unique_total_2025": 12,
      "expected_leads_per_month": 1.0,
      "bonus_low_activity": false,
      "tier_basis": "2025 unique TOTAL properties (deduped by address+ZIP)",
      "note": null
    },
    "98112": {
      "ZIP": 98112,
      "module": "vacant",
      "tier": "Bonus (low activity)",
      "monthly_price_usd": 10,
      "annual_unique_total_2025": 11,
      "expected_leads_per_month": 0.92,
      "bonus_low_activity": true,
      "tier_basis": "2025 unique TOTAL properties (deduped by address+ZIP)",
      "note": "Bonus ZIPs are <1 lead/mo historically; consider offering as add-on or free bonus."
    },
    "98199": {
      "ZIP": 98199,
      "module": "vacant",
      "tier": "Bonus (low activity)",
      "monthly_price_usd": 10,
      "annual_unique_total_2025": 10,
      "expected_leads_per_month": 0.83,
      "bonus_low_activity": true,
      "tier_basis": "2025 unique TOTAL properties (deduped by address+ZIP)",
      "note": "Bonus ZIPs are <1 lead/mo historically; consider offering as add-on or free bonus."
    },
    "98101": {
      "ZIP": 98101,
      "module": "vacant",
      "tier": "Bonus (low activity)",
      "monthly_price_usd": 10,
      "annual_unique_total_2025": 8,
      "expected_leads_per_month": 0.67,
      "bonus_low_activity": true,
      "tier_basis": "2025 unique TOTAL properties (deduped by address+ZIP)",
      "note": "Bonus ZIPs are <1 lead/mo historically; consider offering as add-on or free bonus."
    },
    "98178": {
      "ZIP": 98178,
      "module": "vacant",
      "tier": "Bonus (low activity)",
      "monthly_price_usd": 10,
      "annual_unique_total_2025": 8,
      "expected_leads_per_month": 0.67,
      "bonus_low_activity": true,
      "tier_basis": "2025 unique TOTAL properties (deduped by address+ZIP)",
      "note": "Bonus ZIPs are <1 lead/mo historically; consider offering as add-on or free bonus."
    },
    "98136": {
      "ZIP": 98136,
      "module": "vacant",
      "tier": "Bonus (low activity)",
      "monthly_price_usd": 10,
      "annual_unique_total_2025": 6,
      "expected_leads_per_month": 0.5,
      "bonus_low_activity": true,
      "tier_basis": "2025 unique TOTAL properties (deduped by address+ZIP)",
      "note": "Bonus ZIPs are <1 lead/mo historically; consider offering as add-on or free bonus."
    },
    "98134": {
      "ZIP": 98134,
      "module": "vacant",
      "tier": "Bonus (low activity)",
      "monthly_price_usd": 10,
      "annual_unique_total_2025": 5,
      "expected_leads_per_month": 0.42,
      "bonus_low_activity": true,
      "tier_basis": "2025 unique TOTAL properties (deduped by address+ZIP)",
      "note": "Bonus ZIPs are <1 lead/mo historically; consider offering as add-on or free bonus."
    },
    "98146": {
      "ZIP": 98146,
      "module": "vacant",
      "tier": "Bonus (low activity)",
      "monthly_price_usd": 10,
      "annual_unique_total_2025": 3,
      "expected_leads_per_month": 0.25,
      "bonus_low_activity": true,
      "tier_basis": "2025 unique TOTAL properties (deduped by address+ZIP)",
      "note": "Bonus ZIPs are <1 lead/mo historically; consider offering as add-on or free bonus."
    },
    "98177": {
      "ZIP": 98177,
      "module": "vacant",
      "tier": "Bonus (low activity)",
      "monthly_price_usd": 10,
      "annual_unique_total_2025": 1,
      "expected_leads_per_month": 0.08,
      "bonus_low_activity": true,
      "tier_basis": "2025 unique TOTAL properties (deduped by address+ZIP)",
      "note": "Bonus ZIPs are <1 lead/mo historically; consider offering as add-on or free bonus."
    },
    "98113": {
      "ZIP": 98113,
      "module": "vacant",
      "tier": null,
      "monthly_price_usd": 0,
      "annual_unique_total_2025": 0,
      "expected_leads_per_month": 0.0,
      "bonus_low_activity": false,
      "tier_basis": "2025 unique TOTAL properties (deduped by address+ZIP)",
      "note": null
    },
    "98195": {
      "ZIP": 98195,
      "module": "vacant",
      "tier": null,
      "monthly_price_usd": 0,
      "annual_unique_total_2025": 0,
      "expected_leads_per_month": 0.0,
      "bonus_low_activity": false,
      "tier_basis": "2025 unique TOTAL properties (deduped by address+ZIP)",
      "note": null
    }
  }
}